app/__init__.py
app/__main__.py
app/config.py
app/data_sources.py
app/models.py
app/server.py
app/storage.py
app/tools/__init__.py
app/tools/analysis.py
app/tools/data.py
app/tools/optimization.py
app/tools/portfolio.py
portfolio_mcp-0.0.5.dist-info/METADATA
portfolio_mcp-0.0.5.dist-info/WHEEL
portfolio_mcp-0.0.5.dist-info/entry_points.txt
portfolio_mcp-0.0.5.dist-info/licenses/LICENSE
portfolio_mcp-0.0.5.dist-info/RECORD
