Metadata-Version: 2.4
Name: portfolio-mcp
Version: 0.0.5
Summary: Portfolio analysis MCP server powered by mcp-refcache - Comprehensive portfolio metrics, optimization, and risk analysis
Author-email: l4b4r4b4b4 <lucas.cansino@mail.de>
License-File: LICENSE
Requires-Python: >=3.12
Requires-Dist: fastmcp>=2.14.0
Requires-Dist: finquant-enhanced>=0.7.1
Requires-Dist: mcp-refcache>=0.1.0
Requires-Dist: numpy>=2.0.0
Requires-Dist: pydantic-settings>=2.10.0
Requires-Dist: pydantic>=2.10.0
Requires-Dist: typer>=0.15.0
Requires-Dist: yfinance>=0.2.66
